[
    {
        "date": "2017-01-01",
        "income": 1841.4,
        "outcome": 1881.69
    },
    {
        "date": "2017-02-01",
        "income": 2792,
        "outcome": 1706
    },
    {
        "date": "2017-03-01",
        "income": 1923,
        "outcome": 1566
    },
    {
        "date": "2017-04-01",
        "income": 1907.55,
        "outcome": 1684.98
    },
    {
        "date": "2017-05-01",
        "income": 1961.4,
        "outcome": 1621.16
    },
    {
        "date": "2017-06-01",
        "income": 1900,
        "outcome": 2015.49
    },
    {
        "date": "2017-07-01",
        "income": 2126,
        "outcome": 1286.45
    },
    {
        "date": "2017-08-01",
        "income": 1793,
        "outcome": 2482.47
    },
    {
        "date": "2017-09-01",
        "income": 1752,
        "outcome": 2243.2
    },
    {
        "date": "2017-10-01",
        "income": 1957,
        "outcome": 1102
    },
    {
        "date": "2017-11-01",
        "income": 1983,
        "outcome": 1371
    },
    {
        "date": "2017-12-01",
        "income": 3323,
        "outcome": 815.54
    },
    {
        "date": "2018-01-01",
        "income": 2350.96,
        "outcome": 1253.3
    },
    {
        "date": "2018-02-01",
        "income": 2959.15,
        "outcome": 1802
    },
    {
        "date": "2018-03-01",
        "income": 1891,
        "outcome": 2025.87
    },
    {
        "date": "2018-04-01",
        "income": 2054.5,
        "outcome": 2333.12
    },
    {
        "date": "2018-05-01",
        "income": 1841,
        "outcome": 1632
    },
    {
        "date": "2018-06-01",
        "income": 1974,
        "outcome": 2326.65
    },
    {
        "date": "2018-07-01",
        "income": 2348,
        "outcome": 6656
    },
    {
        "date": "2018-08-01",
        "income": 1981,
        "outcome": 1737
    },
    {
        "date": "2018-09-01",
        "income": 1838,
        "outcome": 1089
    },
    {
        "date": "2018-10-01",
        "income": 1954,
        "outcome": 1946
    },
    {
        "date": "2018-11-01",
        "income": 2017,
        "outcome": 4076
    },
    {
        "date": "2018-12-01",
        "income": 3246,
        "outcome": 293.52
    },
    {
        "date": "2019-01-01",
        "income": 2063.18,
        "outcome": 1445.92
    },
    {
        "date": "2019-02-01",
        "income": 3253,
        "outcome": 1619
    },
    {
        "date": "2019-03-01",
        "income": 2509,
        "outcome": 1050
    },
    {
        "date": "2019-04-01",
        "income": 1974,
        "outcome": 790
    },
    {
        "date": "2019-05-01",
        "income": 1822,
        "outcome": 1220.5
    },
    {
        "date": "2019-06-01",
        "income": 1918,
        "outcome": 1875
    },
    {
        "date": "2019-07-01",
        "income": 2705,
        "outcome": 5946
    },
    {
        "date": "2019-08-01",
        "income": 4507,
        "outcome": 1795
    },
    {
        "date": "2019-09-01",
        "income": 2636,
        "outcome": 3880
    },
    {
        "date": "2019-10-01",
        "income": 2962,
        "outcome": 1338
    },
    {
        "date": "2019-11-01",
        "income": 2065,
        "outcome": 1633
    },
    {
        "date": "2019-12-01",
        "income": 3610,
        "outcome": 1575
    },
    {
        "date": "2020-01-01",
        "income": 1940.5,
        "outcome": 1760
    },
    {
        "date": "2020-02-01",
        "income": 3356,
        "outcome": 1802
    },
    {
        "date": "2020-03-01",
        "income": 1932,
        "outcome": 1062.2
    },
    {
        "date": "2020-04-01",
        "income": 2142,
        "outcome": 1362
    },
    {
        "date": "2020-05-01",
        "income": 1808,
        "outcome": 995
    },
    {
        "date": "2020-06-01",
        "income": 1848,
        "outcome": 1480
    },
    {
        "date": "2020-07-01",
        "income": 2212,
        "outcome": 2871
    },
    {
        "date": "2020-08-01",
        "income": 2508.5,
        "outcome": 8691
    },
    {
        "date": "2020-09-01",
        "income": 2107,
        "outcome": 1602
    },
    {
        "date": "2020-10-01",
        "income": 2099,
        "outcome": 1896
    },
    {
        "date": "2020-11-01",
        "income": 2263,
        "outcome": 1411
    },
    {
        "date": "2020-12-01",
        "income": 3976,
        "outcome": 1331.22
    },
    {
        "date": "2021-01-01",
        "income": 2226,
        "outcome": 1623
    },
    {
        "date": "2021-02-01",
        "income": 3602,
        "outcome": 1300
    },
    {
        "date": "2021-03-01",
        "income": 2992,
        "outcome": 1477
    },
    {
        "date": "2021-04-01",
        "income": 2242,
        "outcome": 1302
    },
    {
        "date": "2021-05-01",
        "income": 2193,
        "outcome": 1764
    },
    {
        "date": "2021-06-01",
        "income": 2164,
        "outcome": 1845
    },
    {
        "date": "2021-07-01",
        "income": 2185,
        "outcome": 2012
    },
    {
        "date": "2021-08-01",
        "income": 4778,
        "outcome": 2435
    },
    {
        "date": "2021-09-01",
        "income": 2550,
        "outcome": 2840
    },
    {
        "date": "2021-10-01",
        "income": 2287,
        "outcome": 1833
    },
    {
        "date": "2021-11-01",
        "income": 2388,
        "outcome": 1745
    },
    {
        "date": "2021-12-01",
        "income": 4056,
        "outcome": 2040
    },
    {
        "date": "2022-01-01",
        "income": 2312,
        "outcome": 1418
    },
    {
        "date": "2022-02-01",
        "income": 3833,
        "outcome": 1656
    },
    {
        "date": "2022-03-01",
        "income": 5297,
        "outcome": 5631
    },
    {
        "date": "2022-04-01",
        "income": 2710,
        "outcome": 1149
    },
    {
        "date": "2022-05-01",
        "income": 3135,
        "outcome": 4385
    },
    {
        "date": "2022-06-01",
        "income": 4309,
        "outcome": 2218
    },
    {
        "date": "2022-07-01",
        "income": 3015,
        "outcome": 2234
    },
    {
        "date": "2022-08-01",
        "income": 2717,
        "outcome": 2442
    },
    {
        "date": "2022-09-01",
        "income": 2629,
        "outcome": 1589
    },
    {
        "date": "2022-10-01",
        "income": 3002,
        "outcome": 1915
    },
    {
        "date": "2022-11-01",
        "income": 2970,
        "outcome": 1928
    },
    {
        "date": "2022-12-01",
        "income": 4792,
        "outcome": 2241
    },
    {
        "date": "2023-01-01",
        "income": 3219,
        "outcome": 2047
    },
    {
        "date": "2023-02-01",
        "income": 2836,
        "outcome": 2524
    },
    {
        "date": "2023-03-01",
        "income": 3257,
        "outcome": 2461
    },
    {
        "date": "2023-04-01",
        "income": 3406,
        "outcome": 3272
    },
    {
        "date": "2023-05-01",
        "income": 7274,
        "outcome": 1498
    },
    {
        "date": "2023-06-01",
        "income": 4670,
        "outcome": 1350
    },
    {
        "date": "2023-07-01",
        "income": 3947,
        "outcome": 2002
    },
    {
        "date": "2023-08-01",
        "income": 3203,
        "outcome": 3233
    },
    {
        "date": "2023-09-01",
        "income": 3442,
        "outcome": 1818
    },
    {
        "date": "2023-10-01",
        "income": 3386,
        "outcome": 1857
    },
    {
        "date": "2023-11-01",
        "income": 3488,
        "outcome": 2295.8
    },
    {
        "date": "2023-12-01",
        "income": 6638,
        "outcome": 1356
    },
    {
        "date": "2024-01-01",
        "income": 3678.17,
        "outcome": 1088.44
    },
    {
        "date": "2024-02-01",
        "income": 3083.34,
        "outcome": 918
    },
    {
        "date": "2024-03-01",
        "income": 3448.32,
        "outcome": 1050
    },
    {
        "date": "2024-04-01",
        "income": 2954.54,
        "outcome": 961
    },
    {
        "date": "2024-05-01",
        "income": 2947,
        "outcome": 842
    },
    {
        "date": "2024-06-01",
        "income": 3285,
        "outcome": 670
    },
    {
        "date": "2024-07-01",
        "income": 5997,
        "outcome": 1071
    },
    {
        "date": "2024-08-01",
        "income": 6644,
        "outcome": 1425
    },
    {
        "date": "2024-09-01",
        "income": 3665,
        "outcome": 950
    },
    {
        "date": "2024-10-01",
        "income": 0,
        "outcome": 820
    },
    {
        "date": "2024-11-01",
        "income": 209,
        "outcome": 709
    },
    {
        "date": "2024-12-01",
        "income": 4252,
        "outcome": 2782
    },
    {
        "date": "2025-01-01",
        "income": 2949,
        "outcome": 900
    },
    {
        "date": "2025-02-01",
        "income": 3690,
        "outcome": 875
    },
    {
        "date": "2025-03-01",
        "income": 3334,
        "outcome": 662
    },
    {
        "date": "2025-04-01",
        "income": 3357,
        "outcome": 1687
    }
]